ballistics/__init__.py
ballistics/__main__.py
ballistics/cli.py
ballistics/external.py
ballistics/extras.py
ballistics/terminal.py
ballistics-0.4.0.dist-info/DESCRIPTION.rst
ballistics-0.4.0.dist-info/METADATA
ballistics-0.4.0.dist-info/RECORD
ballistics-0.4.0.dist-info/WHEEL
ballistics-0.4.0.dist-info/entry_points.txt
ballistics-0.4.0.dist-info/metadata.json
ballistics-0.4.0.dist-info/top_level.txt
