Metadata-Version: 2.0
Name: ballistics
Version: 0.4.0
Summary: A python package for performing exterior, and terminal ballistics calculations.
Home-page: https://github.com/peter-stratton/python-ballistics
Author: Peter Hales Stratton
Author-email: stratton.peter@gmail.com
License: MIT license
Keywords: ballistics,projectile,trajectory
Platform: UNKNOWN
Classifier: Development Status :: 1 - Planning
Classifier: Intended Audience :: Developers
Classifier: License :: OSI Approved :: MIT License
Classifier: Operating System :: Unix
Classifier: Operating System :: POSIX
Classifier: Operating System :: Microsoft :: Windows
Classifier: Programming Language :: Python
Classifier: Programming Language :: Python :: 2.7
Classifier: Programming Language :: Python :: 3
Classifier: Programming Language :: Python :: 3.3
Classifier: Programming Language :: Python :: 3.4
Classifier: Programming Language :: Python :: 3.5
Classifier: Programming Language :: Python :: 3.6
Classifier: Programming Language :: Python :: Implementation :: CPython
Classifier: Topic :: Scientific/Engineering :: Mathematics
Classifier: Topic :: Utilities
